hdh_lib/__init__.py
hdh_lib/file/__init__.py
hdh_lib/file/csv.py
hdh_lib/log.py
hdh_lib/math/__init__.py
hdh_lib/math/math.py
hdh_lib-0.1.0.dist-info/LICENSE.md
hdh_lib-0.1.0.dist-info/METADATA
hdh_lib-0.1.0.dist-info/WHEEL
hdh_lib-0.1.0.dist-info/RECORD
