Metadata-Version: 2.1
Name: hdh-lib
Version: 0.1.0
Summary: Support libraries for High Desert Hacker python programs.
Author: High Desert Hacker
Author-email: highdeserthacker@gmail.com
Requires-Python: >=3.6,<4.0
Classifier: Programming Language :: Python :: 3
Classifier: Programming Language :: Python :: 3.6
Classifier: Programming Language :: Python :: 3.7
Classifier: Programming Language :: Python :: 3.8
Classifier: Programming Language :: Python :: 3.9
Classifier: Programming Language :: Python :: 3.10
Classifier: Programming Language :: Python :: 3.11
